espnet_onnx/__init__.py
espnet_onnx/asr/__init__.py
espnet_onnx/asr/abs_asr_model.py
espnet_onnx/asr/asr_model.py
espnet_onnx/asr/asr_streaming.py
espnet_onnx/asr/beam_search/__init__.py
espnet_onnx/asr/beam_search/batch_beam_search.py
espnet_onnx/asr/beam_search/batch_beam_search_online.py
espnet_onnx/asr/beam_search/batch_beam_search_online_sim.py
espnet_onnx/asr/beam_search/beam_search.py
espnet_onnx/asr/beam_search/beam_search_transducer.py
espnet_onnx/asr/beam_search/hyps.py
espnet_onnx/asr/frontend/__init__.py
espnet_onnx/asr/frontend/frontend.py
espnet_onnx/asr/frontend/torch_frontend.py
espnet_onnx/asr/frontend/default/__init__.py
espnet_onnx/asr/frontend/default/default_frontend.py
espnet_onnx/asr/frontend/default/logmel.py
espnet_onnx/asr/frontend/default/stft.py
espnet_onnx/asr/frontend/normalize/__init__.py
espnet_onnx/asr/frontend/normalize/global_mvn.py
espnet_onnx/asr/frontend/normalize/utterance_mvn.py
espnet_onnx/asr/frontend/s3prl/__init__.py
espnet_onnx/asr/frontend/s3prl/hubert.py
espnet_onnx/asr/model/__init__.py
espnet_onnx/asr/model/decoder.py
espnet_onnx/asr/model/encoder.py
espnet_onnx/asr/model/joint_network.py
espnet_onnx/asr/model/lm.py
espnet_onnx/asr/model/decoders/__init__.py
espnet_onnx/asr/model/decoders/rnn.py
espnet_onnx/asr/model/decoders/transducer.py
espnet_onnx/asr/model/decoders/xformer.py
espnet_onnx/asr/model/encoders/__init__.py
espnet_onnx/asr/model/encoders/encoder.py
espnet_onnx/asr/model/encoders/streaming.py
espnet_onnx/asr/model/lms/__init__.py
espnet_onnx/asr/model/lms/seqrnn_lm.py
espnet_onnx/asr/model/lms/transformer_lm.py
espnet_onnx/asr/postprocess/__init__.py
espnet_onnx/asr/postprocess/build_tokenizer.py
espnet_onnx/asr/postprocess/token_id_converter.py
espnet_onnx/asr/postprocess/tokenizers/__init__.py
espnet_onnx/asr/postprocess/tokenizers/char_tokenizer.py
espnet_onnx/asr/postprocess/tokenizers/phoneme_tokenizer.py
espnet_onnx/asr/postprocess/tokenizers/sentencepiece_tokenizer.py
espnet_onnx-0.2.1.dist-info/LICENSE
espnet_onnx-0.2.1.dist-info/METADATA
espnet_onnx-0.2.1.dist-info/WHEEL
espnet_onnx-0.2.1.dist-info/top_level.txt
espnet_onnx-0.2.1.dist-info/RECORD
