Metadata-Version: 2.1
Name: espnet_onnx
Version: 0.2.1
Summary: ONNX Wrapper for ESPnet
Home-page: https://github.com/Masao-Someki/espnet_onnx
Author: Masao Someki
Author-email: masao.someki@gmail.com
License: MIT
Keywords: espnet onnxruntime
Classifier: Programming Language :: Python
Classifier: Programming Language :: Python :: 3
Classifier: Programming Language :: Python :: 3.8
Classifier: Programming Language :: Python :: 3.9
Classifier: Programming Language :: Python :: 3.10
Classifier: Development Status :: 5 - Production/Stable
Classifier: Intended Audience :: Developers
Classifier: Operating System :: OS Independent
Classifier: License :: OSI Approved :: MIT License
Classifier: Topic :: Software Development :: Libraries :: Python Modules
Requires-Python: >=3.7.0
License-File: LICENSE
Requires-Dist: setuptools >=38.5.1
Requires-Dist: librosa >=0.8.0
Requires-Dist: onnxruntime
Requires-Dist: sentencepiece !=0.1.92,>=0.1.91
Requires-Dist: typeguard ==2.13.0
Requires-Dist: PyYAML >=5.1.2
Requires-Dist: g2p-en
Requires-Dist: jamo ==0.4.1
Requires-Dist: six
Requires-Dist: numpy
Requires-Dist: espnet-tts-frontend
